mjdb/__init__.py
mjdb/base/__init__.py
mjdb/base/mixin/__init__.py
mjdb/base/mixin/from_dataframe_mixin.py
mjdb/base/mixin/model_to_dict_mixin.py
mjdb/model/__init__.py
mjdb/model/abstract/__init__.py
mjdb/model/abstract/abstract_model.py
mjdb/model/base/__init__.py
mjdb/model/base/base_model.py
mjdb/model/daily_etf_constituents.py
mjdb/model/daily_etf_ohlcv.py
mjdb/model/daily_kor_investor_trading_volume_summary.py
mjdb/model/daily_kor_stock_analysis_summary.py
mjdb/model/daily_shareholder_ownership.py
mjdb/model/daily_stock_rise_reason_keywords.py
mjdb/model/utiles/__init__.py
mjdb/model/utiles/convert_df_to_models.py
mjdb/model/utiles/df_to_model_instances.py
mjdb/repositories/__init__.py
mjdb/repositories/abstract/__init__.py
mjdb/repositories/abstract/abstract_repository.py
mjdb/repositories/base/__init__.py
mjdb/repositories/base/base_repository.py
mjdb/repositories/etf_constituents_repository.py
mjdb/repositories/etf_ohlcv_repository.py
mjdb/repositories/investor_trading_volume_repository.py
mjdb/repositories/kor_stock_analysis_summary_repository.py
mjdb/repositories/shareholder_ownership_repository.py
mjdb/repositories/stock_rise_reason_keywords_repository.py
mjdb/session/__init__.py
mjdb/session/abstract/__init__.py
mjdb/session/abstract/abstract_db_session.py
mjdb/session/base/__init__.py
mjdb/session/base/base_session.py
mjdb/session/sql_alchemy_db_session.py
mjdb/session/types/__init__.py
mjdb/session/types/engine_config.py
mjdb/session/types/session_config.py
mjdb/session/types/session_context.py
mjdb-0.0.8.dist-info/LICENSE
mjdb-0.0.8.dist-info/METADATA
mjdb-0.0.8.dist-info/WHEEL
mjdb-0.0.8.dist-info/RECORD
