Metadata-Version: 2.3
Name: mjdb
Version: 0.0.8
Summary: pymysql, sqlalchemy, pandas 기반의 데이터베이스 렙핑 라이브러리
License: SEE LICENSE FILE
Author: devmjun
Author-email: dev.mjun@gmail.com
Requires-Python: >=3.10, <4
Classifier: Programming Language :: Python :: 3.10
Classifier: Programming Language :: Python :: 3.11
Classifier: Programming Language :: Python :: 3.12
Classifier: Programming Language :: Python :: 3.13
Classifier: Programming Language :: Python :: 3 :: Only
Requires-Dist: mjkit (>=0.0.19)
Requires-Dist: pandas (>=2.3.0,<3.0.0)
Requires-Dist: pymysql (>=1.1.1,<2.0.0)
Requires-Dist: sqlalchemy (>=2.0.41,<3.0.0)
Requires-Dist: tenacity (>=9.1.2,<10.0.0)
Requires-Dist: tqdm (>=4.67.1,<5.0.0)
